cbg/__init__.py
cbg/__main__.py
cbg/bitvector.py
cbg/bytearray.py
cbg/decorators.py
cbg/version.py
cbg/cmds/__init__.py
cbg/cmds/bitcount.py
cbg/cmds/bloom.py
cbg/cmds/build.py
cbg/cmds/compress.py
cbg/cmds/delete.py
cbg/cmds/dump.py
cbg/cmds/insert.py
cbg/cmds/jaccard_index.py
cbg/cmds/kmers.py
cbg/cmds/load.py
cbg/cmds/merge.py
cbg/cmds/rowjoin.py
cbg/cmds/samples.py
cbg/cmds/search.py
cbg/cmds/shutdown.py
cbg/cmds/stats.py
cbg/cmds/uncompress.py
cbg/graph/__init__.py
cbg/graph/base.py
cbg/graph/probabilistic.py
cbg/matrix/__init__.py
cbg/matrix/transpose.py
cbg/sketch/__init__.py
cbg/sketch/hll.py
cbg/sketch/minhash.py
cbg/storage/__init__.py
cbg/storage/base.py
cbg/storage/graph/base.py
cbg/storage/graph/probabilistic.py
cbg/tasks/__init__.py
cbg/tasks/tasks.py
cbg/utils/__init__.py
cbg/utils/cortex.py
cbg/utils/fncts.py
cbg-0.1.2.dev1.dist-info/DESCRIPTION.rst
cbg-0.1.2.dev1.dist-info/METADATA
cbg-0.1.2.dev1.dist-info/RECORD
cbg-0.1.2.dev1.dist-info/WHEEL
cbg-0.1.2.dev1.dist-info/entry_points.txt
cbg-0.1.2.dev1.dist-info/metadata.json
cbg-0.1.2.dev1.dist-info/top_level.txt
