Metadata-Version: 2.0
Name: cbg
Version: 0.1.2.dev1
Summary: Coloured Bloom Graphs - Low memory multicolour de Bruijn graphs for indexing large collections of genomes
Home-page: http://github.com/phelimb/cbg
Author: Phelim Bradley
Author-email: wave@phel.im
License: MIT
Keywords: DBG coloured de bruijn graphs sequence search
Platform: UNKNOWN
Classifier: Development Status :: 3 - Alpha
Classifier: License :: OSI Approved :: MIT License
Classifier: Programming Language :: Python :: 3
Classifier: Programming Language :: Python :: 3.2
Classifier: Programming Language :: Python :: 3.3
Classifier: Programming Language :: Python :: 3.4
Classifier: Programming Language :: Python :: 3.5
Classifier: Programming Language :: Python :: 3.6
Requires-Dist: HLL
Requires-Dist: biopython
Requires-Dist: bitarray
Requires-Dist: bitstring
Requires-Dist: bsddb3
Requires-Dist: celery
Requires-Dist: codecov
Requires-Dist: crc16
Requires-Dist: credis
Requires-Dist: cython
Requires-Dist: flask
Requires-Dist: hiredis
Requires-Dist: hypothesis
Requires-Dist: mmh3
Requires-Dist: numpy
Requires-Dist: psutil
Requires-Dist: pytest
Requires-Dist: pytest-cov
Requires-Dist: redis
Requires-Dist: uwsgi
